<?xml version="1.0" encoding="utf-8"?>
<pages>
	<nextid>4002</nextid>
	<page id="1" type="leaf" path="1.asp" eng="SST Deskbooks 1" fre="Manuels d'instructions Atrium" node="0" pgCSS="" contentUpdated="5/6/2013 9:23:45 AM" contentUpdatedPerson="JEAN">
		<access contentAccessed="9/26/2012 6:13:33 PM" contentAccessedPerson="JXL811"/>
		<access contentAccessed="9/26/2012 6:18:56 PM" contentAccessedPerson="JXL811"/>
		<access contentAccessed="9/26/2012 6:19:45 PM" contentAccessedPerson="JXL811"/>
		<access contentAccessed="9/26/2012 6:19:46 PM" contentAccessedPerson="JXL811"/>
		<access contentAccessed="9/26/2012 7:37:43 PM" contentAccessedPerson="JXL811"/>
		<access contentAccessed="9/26/2012 8:21:05 PM" contentAccessedPerson="JXL811"/>
		<access contentAccessed="9/26/2012 8:25:08 PM" contentAccessedPerson="JXL811"/>
		<access contentAccessed="9/27/2012 10:57:44 AM" contentAccessedPerson="JXL811"/>
		<access contentAccessed="9/27/2012 11:11:25 AM" contentAccessedPerson="JXL811"/>
		<access contentAccessed="9/27/2012 11:23:43 AM" contentAccessedPerson="JXL811"/>
		<access contentAccessed="11/21/2012 10:08:24 AM" contentAccessedPerson="PHILIP.STANG"/><access contentAccessed="11/21/2012 10:13:10 AM" contentAccessedPerson="PHILIP.STANG"/><access contentAccessed="11/21/2012 12:03:48 PM" contentAccessedPerson="PHILIP.STANG"/><access contentAccessed="11/22/2012 9:32:41 AM" contentAccessedPerson="PHILIP.STANG"/><access contentAccessed="11/22/2012 9:33:32 AM" contentAccessedPerson="PHILIP.STANG"/><access contentAccessed="11/22/2012 10:03:31 AM" contentAccessedPerson="PHILIP.STANG"/><access contentAccessed="11/22/2012 3:35:10 PM" contentAccessedPerson="PHILIP.STANG"/><access contentAccessed="11/22/2012 3:46:38 PM" contentAccessedPerson="PHILIP.STANG"/><access contentAccessed="12/6/2012 2:01:22 PM" contentAccessedPerson="PHILIP.STANG"/><access contentAccessed="1/28/2013 12:16:10 PM" contentAccessedPerson="JEAN"/><access contentAccessed="1/28/2013 12:19:52 PM" contentAccessedPerson="JEAN"/><access contentAccessed="1/28/2013 1:07:52 PM" contentAccessedPerson="JEAN"/><access contentAccessed="1/28/2013 1:07:57 PM" contentAccessedPerson="JEAN"/><access contentAccessed="1/28/2013 1:21:48 PM" contentAccessedPerson="JEAN"/><access contentAccessed="1/28/2013 1:21:52 PM" contentAccessedPerson="JEAN"/><access contentAccessed="1/29/2013 9:40:19 AM" contentAccessedPerson="JEAN"/><access contentAccessed="1/29/2013 9:40:28 AM" contentAccessedPerson="JEAN"/><access contentAccessed="1/29/2013 9:40:53 AM" contentAccessedPerson="JEAN"/><access contentAccessed="5/6/2013 9:11:25 AM" contentAccessedPerson="JEAN"/><access contentAccessed="5/6/2013 9:22:48 AM" contentAccessedPerson="JEAN"/><access contentAccessed="8/19/2013 10:28:03 AM" contentAccessedPerson=""/></page>
	<page id="8071" type="node" path="8071.asp" eng="Atrium User Guide" fre="Atrium User Guide"/>
	<page id="8072" type="node" path="8072.asp" eng="Getting Started" fre="Getting Started" contentUpdated="9/27/2012 7:57:28 AM" contentUpdatedPerson="JXL811">
		<access contentAccessed="9/27/2012 7:57:19 AM" contentAccessedPerson="JXL811"/>
		<access contentAccessed="9/27/2012 7:57:24 AM" contentAccessedPerson="JXL811"/>
	</page>
	<page id="8073" type="node" path="8073.asp" eng="How to ..." fre="How to ..."/>
	<page id="8079" type="leaf" path="8079.asp" eng="Deskbook Structure" fre="Deskbook Structure" contentUpdated="1/7/2013 3:00:45 PM" contentUpdatedPerson="" pgCSS="">
		<access contentAccessed="9/26/2012 10:15:59 PM" contentAccessedPerson="JXL811"/>
		<access contentAccessed="9/26/2012 10:16:16 PM" contentAccessedPerson="JXL811"/>
		<access contentAccessed="9/27/2012 7:49:16 AM" contentAccessedPerson="JXL811"/>
		<access contentAccessed="9/27/2012 7:49:21 AM" contentAccessedPerson="JXL811"/>
		<access contentAccessed="9/27/2012 11:29:26 AM" contentAccessedPerson="JXL811"/>
		<access contentAccessed="9/27/2012 11:37:50 AM" contentAccessedPerson="JXL811"/>
		<access contentAccessed="10/1/2012 9:18:51 AM" contentAccessedPerson="JXL811"/>
		<access contentAccessed="10/1/2012 9:18:58 AM" contentAccessedPerson="JXL811"/>
		<access contentAccessed="10/1/2012 2:05:48 PM" contentAccessedPerson="JXL811"/><access contentAccessed="10/1/2012 2:08:18 PM" contentAccessedPerson="JXL811"/><access contentAccessed="11/21/2012 10:16:30 AM" contentAccessedPerson="PHILIP.STANG"/><access contentAccessed="11/21/2012 12:03:34 PM" contentAccessedPerson="PHILIP.STANG"/><access contentAccessed="11/21/2012 4:23:30 PM" contentAccessedPerson="PHILIP.STANG"/><access contentAccessed="11/22/2012 9:41:18 AM" contentAccessedPerson="PHILIP.STANG"/><access contentAccessed="11/22/2012 10:04:25 AM" contentAccessedPerson="PHILIP.STANG"/><access contentAccessed="11/24/2012 2:54:02 PM" contentAccessedPerson="PHILIP.STANG"/><access contentAccessed="11/25/2012 1:50:07 PM" contentAccessedPerson="JXL811"/><access contentAccessed="11/25/2012 1:50:20 PM" contentAccessedPerson="JXL811"/><access contentAccessed="11/25/2012 1:50:36 PM" contentAccessedPerson="JXL811"/><access contentAccessed="11/25/2012 2:51:00 PM" contentAccessedPerson="JXL811"/><access contentAccessed="11/25/2012 2:51:04 PM" contentAccessedPerson="PHILIP.STANG"/><access contentAccessed="11/25/2012 2:54:17 PM" contentAccessedPerson="JXL811"/><access contentAccessed="11/25/2012 3:10:41 PM" contentAccessedPerson="JXL811"/><access contentAccessed="11/25/2012 3:10:51 PM" contentAccessedPerson="JXL811"/><access contentAccessed="11/25/2012 3:11:27 PM" contentAccessedPerson="JXL811"/><access contentAccessed="11/25/2012 3:12:16 PM" contentAccessedPerson="JXL811"/><access contentAccessed="11/25/2012 3:13:28 PM" contentAccessedPerson="JXL811"/><access contentAccessed="11/25/2012 3:14:06 PM" contentAccessedPerson="JXL811"/><access contentAccessed="11/25/2012 3:15:08 PM" contentAccessedPerson="JXL811"/><access contentAccessed="11/25/2012 3:15:31 PM" contentAccessedPerson="JXL811"/><access contentAccessed="11/25/2012 3:15:38 PM" contentAccessedPerson="JXL811"/><access contentAccessed="11/25/2012 3:16:11 PM" contentAccessedPerson="JXL811"/><access contentAccessed="11/25/2012 3:16:28 PM" contentAccessedPerson="JXL811"/><access contentAccessed="11/25/2012 3:17:14 PM" contentAccessedPerson="JXL811"/><access contentAccessed="11/25/2012 3:17:34 PM" contentAccessedPerson="JXL811"/><access contentAccessed="11/25/2012 3:18:01 PM" contentAccessedPerson="JXL811"/><access contentAccessed="11/25/2012 3:18:23 PM" contentAccessedPerson="JXL811"/><access contentAccessed="11/25/2012 3:19:04 PM" contentAccessedPerson="JXL811"/><access contentAccessed="11/25/2012 3:19:27 PM" contentAccessedPerson="JXL811"/><access contentAccessed="11/25/2012 3:19:46 PM" contentAccessedPerson="JXL811"/><access contentAccessed="11/25/2012 3:21:24 PM" contentAccessedPerson="JXL811"/><access contentAccessed="11/25/2012 3:22:03 PM" contentAccessedPerson="JXL811"/><access contentAccessed="11/25/2012 3:22:44 PM" contentAccessedPerson="JXL811"/><access contentAccessed="11/25/2012 3:23:29 PM" contentAccessedPerson="JXL811"/><access contentAccessed="11/25/2012 3:24:20 PM" contentAccessedPerson="JXL811"/><access contentAccessed="11/26/2012 2:46:59 PM" contentAccessedPerson="PHILIP.STANG"/><access contentAccessed="11/26/2012 2:48:51 PM" contentAccessedPerson="PHILIP.STANG"/><access contentAccessed="11/27/2012 1:49:24 PM" contentAccessedPerson="PHILIP.STANG"/><access contentAccessed="11/27/2012 1:53:26 PM" contentAccessedPerson="PHILIP.STANG"/><access contentAccessed="1/7/2013 3:00:37 PM" contentAccessedPerson=""/></page>
	<page id="8080" type="leaf" path="8080.asp" eng="Help Triangle" fre="Help Triangle" contentUpdated="11/22/2012 10:05:31 AM" contentUpdatedPerson="PHILIP.STANG">
		<access contentAccessed="9/26/2012 10:19:03 PM" contentAccessedPerson="JXL811"/>
		<access contentAccessed="9/26/2012 10:19:15 PM" contentAccessedPerson="JXL811"/>
		<access contentAccessed="9/27/2012 7:49:35 AM" contentAccessedPerson="JXL811"/>
		<access contentAccessed="9/27/2012 7:49:41 AM" contentAccessedPerson="JXL811"/>
		<access contentAccessed="9/28/2012 11:34:33 AM" contentAccessedPerson="JXL811"/>
		<access contentAccessed="10/1/2012 1:40:56 PM" contentAccessedPerson="JXL811"/><access contentAccessed="11/21/2012 11:26:12 AM" contentAccessedPerson="PHILIP.STANG"/><access contentAccessed="11/22/2012 9:47:29 AM" contentAccessedPerson="PHILIP.STANG"/><access contentAccessed="11/22/2012 10:01:25 AM" contentAccessedPerson="PHILIP.STANG"/><access contentAccessed="11/22/2012 10:21:13 AM" contentAccessedPerson="PHILIP.STANG"/><access contentAccessed="11/22/2012 11:25:55 AM" contentAccessedPerson="PHILIP.STANG"/><access contentAccessed="11/22/2012 12:04:59 PM" contentAccessedPerson="PHILIP.STANG"/></page>
	<page id="8081" type="node" path="8081.asp" eng="Conceptual Foundation of Atrium" fre="Conceptual Foundation of Atrium"/>
	<page id="8082" type="leaf" path="8082.asp" eng="Introduction" fre="Introduction" contentUpdated="11/22/2012 9:45:43 AM" contentUpdatedPerson="PHILIP.STANG">
		<access contentAccessed="9/26/2012 10:19:50 PM" contentAccessedPerson="JXL811"/>
		<access contentAccessed="9/27/2012 7:49:55 AM" contentAccessedPerson="JXL811"/>
		<access contentAccessed="9/27/2012 7:50:01 AM" contentAccessedPerson="JXL811"/>
		<access contentAccessed="9/28/2012 11:12:26 AM" contentAccessedPerson="JXL811"/>
		<access contentAccessed="10/1/2012 1:40:01 PM" contentAccessedPerson="JXL811"/><access contentAccessed="11/21/2012 10:15:47 AM" contentAccessedPerson="PHILIP.STANG"/><access contentAccessed="11/21/2012 11:09:35 AM" contentAccessedPerson="PHILIP.STANG"/><access contentAccessed="11/21/2012 12:03:19 PM" contentAccessedPerson="PHILIP.STANG"/><access contentAccessed="11/22/2012 9:43:10 AM" contentAccessedPerson="PHILIP.STANG"/><access contentAccessed="11/24/2012 2:54:23 PM" contentAccessedPerson="PHILIP.STANG"/><access contentAccessed="1/28/2013 10:35:03 PM" contentAccessedPerson="CWEEKES"/><access contentAccessed="1/28/2013 10:35:16 PM" contentAccessedPerson="CWEEKES"/></page>
	<page id="8083" type="leaf" path="8083.asp" eng="Records Management Principles" fre="Records Management Principles" contentUpdated="11/22/2012 9:47:03 AM" contentUpdatedPerson="PHILIP.STANG">
		<access contentAccessed="9/26/2012 10:20:21 PM" contentAccessedPerson="JXL811"/>
		<access contentAccessed="9/27/2012 7:50:11 AM" contentAccessedPerson="JXL811"/>
		<access contentAccessed="9/27/2012 7:50:18 AM" contentAccessedPerson="JXL811"/>
		<access contentAccessed="9/28/2012 11:20:53 AM" contentAccessedPerson="JXL811"/>
		<access contentAccessed="11/21/2012 11:12:27 AM" contentAccessedPerson="PHILIP.STANG"/><access contentAccessed="11/22/2012 9:46:02 AM" contentAccessedPerson="PHILIP.STANG"/></page>
	<page id="8084" type="leaf" path="8084.asp" eng="SST Records Retention Policy" fre="SST Records Retention Policy" contentUpdated="9/27/2012 7:50:37 AM" contentUpdatedPerson="JXL811">
		<access contentAccessed="9/27/2012 7:50:29 AM" contentAccessedPerson="JXL811"/>
		<access contentAccessed="9/27/2012 7:50:33 AM" contentAccessedPerson="JXL811"/>
		<access contentAccessed="11/22/2012 9:47:06 AM" contentAccessedPerson="PHILIP.STANG"/></page>
	<page id="8086" type="leaf" path="8086.asp" eng="Known Issues" fre="Known Issues" contentUpdated="9/28/2012 11:53:41 AM" contentUpdatedPerson="JXL811">
		<access contentAccessed="9/26/2012 10:22:49 PM" contentAccessedPerson="JXL811"/>
		<access contentAccessed="9/27/2012 7:51:05 AM" contentAccessedPerson="JXL811"/>
		<access contentAccessed="9/27/2012 7:51:12 AM" contentAccessedPerson="JXL811"/>
		<access contentAccessed="9/28/2012 11:47:57 AM" contentAccessedPerson="JXL811"/>
	</page>
	<page id="8087" type="leaf" path="8087.asp" eng="Whats New" fre="Whats New" contentUpdated="9/28/2012 11:57:51 AM" contentUpdatedPerson="JXL811">
		<access contentAccessed="9/26/2012 10:24:00 PM" contentAccessedPerson="JXL811"/>
		<access contentAccessed="9/26/2012 10:24:29 PM" contentAccessedPerson="JXL811"/>
		<access contentAccessed="9/27/2012 7:51:25 AM" contentAccessedPerson="JXL811"/>
		<access contentAccessed="9/27/2012 7:51:31 AM" contentAccessedPerson="JXL811"/>
		<access contentAccessed="9/28/2012 11:55:16 AM" contentAccessedPerson="JXL811"/>
	</page>
	<page id="8088" type="leaf" path="8088.asp" eng="Roles and Responsibilities [Update for SST]" fre="Roles and Responsibilities" contentUpdated="11/21/2012 11:32:55 AM" contentUpdatedPerson="PHILIP.STANG">
		<access contentAccessed="9/26/2012 10:25:27 PM" contentAccessedPerson="JXL811"/>
		<access contentAccessed="9/27/2012 7:51:40 AM" contentAccessedPerson="JXL811"/>
		<access contentAccessed="9/27/2012 7:51:45 AM" contentAccessedPerson="JXL811"/>
		<access contentAccessed="9/27/2012 7:51:51 AM" contentAccessedPerson="JXL811"/>
		<access contentAccessed="9/28/2012 11:53:53 AM" contentAccessedPerson="JXL811"/>
		<access contentAccessed="11/21/2012 11:31:50 AM" contentAccessedPerson="PHILIP.STANG"/></page>
	<page id="8089" type="leaf" path="8089.asp" eng="Overview of Atrium (GS001)" fre="Overview of Atrium (GS001)" contentUpdated="11/21/2012 6:07:07 PM" contentUpdatedPerson="">
		<access contentAccessed="9/27/2012 7:52:49 AM" contentAccessedPerson="JXL811"/>
		<access contentAccessed="9/27/2012 7:52:58 AM" contentAccessedPerson="JXL811"/>
		<access contentAccessed="9/27/2012 7:53:00 AM" contentAccessedPerson="JXL811"/>
		<access contentAccessed="9/27/2012 7:53:06 AM" contentAccessedPerson="JXL811"/>
		<access contentAccessed="9/28/2012 11:58:04 AM" contentAccessedPerson="JXL811"/>
		<access contentAccessed="9/28/2012 12:09:49 PM" contentAccessedPerson="JXL811"/>
		<access contentAccessed="10/2/2012 10:36:06 PM" contentAccessedPerson="JXL811"/><access contentAccessed="11/21/2012 11:59:32 AM" contentAccessedPerson="PHILIP.STANG"/><access contentAccessed="11/21/2012 12:04:52 PM" contentAccessedPerson="PHILIP.STANG"/><access contentAccessed="11/21/2012 4:10:27 PM" contentAccessedPerson="PHILIP.STANG"/><access contentAccessed="11/21/2012 4:21:52 PM" contentAccessedPerson="PHILIP.STANG"/><access contentAccessed="1/28/2013 1:51:19 PM" contentAccessedPerson="JEAN"/><access contentAccessed="1/28/2013 2:23:52 PM" contentAccessedPerson="JEAN"/><access contentAccessed="5/6/2013 9:12:50 AM" contentAccessedPerson="JEAN"/></page>
	<page id="8092" type="leaf" path="8092.asp" eng="Using Panes (GS002)" fre="Using Panes (GS002)" contentUpdated="11/22/2012 11:24:17 AM" contentUpdatedPerson="PHILIP.STANG">
		<access contentAccessed="9/27/2012 7:53:12 AM" contentAccessedPerson="JXL811"/>
		<access contentAccessed="9/27/2012 7:53:17 AM" contentAccessedPerson="JXL811"/>
		<access contentAccessed="9/28/2012 12:11:12 PM" contentAccessedPerson="JXL811"/>
		<access contentAccessed="11/21/2012 1:21:16 PM" contentAccessedPerson="PHILIP.STANG"/><access contentAccessed="11/22/2012 10:20:25 AM" contentAccessedPerson="PHILIP.STANG"/><access contentAccessed="11/22/2012 10:38:04 AM" contentAccessedPerson="PHILIP.STANG"/><access contentAccessed="2/8/2013 1:42:26 PM" contentAccessedPerson=""/></page>
	<page id="8093" type="leaf" path="8093.asp" eng="Using Grids (GS003)" fre="Using Grids (GS003)" contentUpdated="11/22/2012 11:56:37 AM" contentUpdatedPerson="PHILIP.STANG">
		<access contentAccessed="9/27/2012 7:53:27 AM" contentAccessedPerson="JXL811"/>
		<access contentAccessed="9/27/2012 7:53:32 AM" contentAccessedPerson="JXL811"/>
		<access contentAccessed="9/28/2012 12:11:39 PM" contentAccessedPerson="JXL811"/>
		<access contentAccessed="11/22/2012 11:24:50 AM" contentAccessedPerson="PHILIP.STANG"/></page>
	<page id="8094" type="leaf" path="8094.asp" eng="Using Trees (GS004)" fre="Using Trees (GS004)" contentUpdated="1/24/2013 9:52:46 PM" contentUpdatedPerson="" pgCSS="">
		<access contentAccessed="9/27/2012 7:53:42 AM" contentAccessedPerson="JXL811"/>
		<access contentAccessed="9/27/2012 7:53:48 AM" contentAccessedPerson="JXL811"/>
		<access contentAccessed="9/28/2012 12:11:55 PM" contentAccessedPerson="JXL811"/>
		<access contentAccessed="11/22/2012 11:57:10 AM" contentAccessedPerson="PHILIP.STANG"/><access contentAccessed="11/22/2012 1:40:40 PM" contentAccessedPerson="PHILIP.STANG"/><access contentAccessed="11/22/2012 2:21:50 PM" contentAccessedPerson="PHILIP.STANG"/><access contentAccessed="1/24/2013 9:46:51 PM" contentAccessedPerson=""/></page>
	<page id="8095" type="leaf" path="8095.asp" eng="Explanation of Activities (GS005)" fre="Explanation of Activities (GS005)" contentUpdated="1/24/2013 10:00:35 PM" contentUpdatedPerson="" pgCSS="">
		<access contentAccessed="9/27/2012 7:53:58 AM" contentAccessedPerson="JXL811"/>
		<access contentAccessed="9/27/2012 7:54:03 AM" contentAccessedPerson="JXL811"/>
		<access contentAccessed="9/28/2012 12:12:33 PM" contentAccessedPerson="JXL811"/>
		<access contentAccessed="11/21/2012 12:43:38 PM" contentAccessedPerson="PHILIP.STANG"/><access contentAccessed="11/22/2012 2:56:26 PM" contentAccessedPerson="PHILIP.STANG"/><access contentAccessed="11/22/2012 3:31:55 PM" contentAccessedPerson="PHILIP.STANG"/><access contentAccessed="11/22/2012 3:45:10 PM" contentAccessedPerson="PHILIP.STANG"/><access contentAccessed="11/26/2012 2:01:06 PM" contentAccessedPerson="PHILIP.STANG"/><access contentAccessed="11/26/2012 2:03:32 PM" contentAccessedPerson="PHILIP.STANG"/><access contentAccessed="1/24/2013 9:59:22 PM" contentAccessedPerson=""/><access contentAccessed="1/24/2013 10:06:10 PM" contentAccessedPerson=""/></page>
	<page id="8096" type="node" path="8096.asp" eng="Policies &amp; Procedures Deskbook" fre="Policies &amp; Procedures Deskbook"/>
	<page id="8097" type="node" path="8097.asp" eng="Officer Deskbooks" fre="Officer Deskbooks"/>
	<page id="8098" type="node" path="8098.asp" eng="Tribunal Members' Deskbook" fre="Tribunal Members' Deskbook"/>
	<page id="8099" type="node" path="8099.asp" eng="Case Officer's Deskbook" fre="Case Officer's Deskbook"/>
	<page id="8100" type="node" path="8100.asp" eng="Reception Deskbook" fre="Reception Deskbook"/>
	<page id="8101" type="node" path="8101.asp" eng="Support Clerk's Deskbook" fre="Support Clerk's Deskbook"/>
	<page id="8102" type="node" path="8102.asp" eng="EI Appeal to General Division Processes" fre="EI Appeal to General Division Processes"/>
	<page id="8104" type="node" path="8104.asp" eng="Introduction" fre="Introduction"/>
	<page id="8105" type="node" path="8105.asp" eng="CPP/OAS Appeal to General Division Processes" fre="CPP/OAS Appeal to General Division Processes"/>
	<page id="8106" type="node" path="8106.asp" eng="Appeal Division Processes" fre="Appeal Division Processes"/>
	<page id="8107" type="node" path="8107.asp" eng="Screens" fre="Screens"/>
	<page id="8109" type="node" path="8109.asp" eng="Main Screen and Panes" fre="Main Screens and Panes"/>
	<page id="8110" type="node" path="8110.asp" eng="File-based Screens" fre="File-based Screens"/>
	<page id="8111" type="node" path="8111.asp" eng="Non-file-based Screens" fre="Non-file-based Screens"/>
	<page id="8112" type="leaf" path="8112.asp" eng="Main Atrium Screen (SC001)" fre="Main Atrium Screen (SC001)" contentUpdated="1/29/2013 7:28:47 PM" contentUpdatedPerson="PHILIP.STANG" pgCSS="">
		<access contentAccessed="9/28/2012 12:53:14 PM" contentAccessedPerson="JXL811"/>
		<access contentAccessed="11/28/2012 10:43:33 PM" contentAccessedPerson="PHILIP.STANG"/><access contentAccessed="1/23/2013 2:09:47 PM" contentAccessedPerson=""/><access contentAccessed="1/24/2013 8:58:38 AM" contentAccessedPerson="PHILIP.STANG"/><access contentAccessed="1/28/2013 1:36:49 PM" contentAccessedPerson="JEAN"/><access contentAccessed="1/28/2013 2:17:26 PM" contentAccessedPerson="JEAN"/><access contentAccessed="1/28/2013 2:25:00 PM" contentAccessedPerson="JEAN"/><access contentAccessed="1/29/2013 5:00:31 PM" contentAccessedPerson=""/><access contentAccessed="1/29/2013 7:22:03 PM" contentAccessedPerson="PHILIP.STANG"/></page>
	<page id="8113" type="leaf" path="8113.asp" eng="Officer Toolkit Pane (SC002)" fre="Officer Toolkit Pane" contentUpdated="1/29/2013 5:25:50 PM" contentUpdatedPerson="PHILIP.STANG" pgCSS="">
		<access contentAccessed="9/28/2012 12:56:03 PM" contentAccessedPerson="JXL811"/>
		<access contentAccessed="11/28/2012 11:19:17 PM" contentAccessedPerson="PHILIP.STANG"/><access contentAccessed="1/24/2013 9:06:49 AM" contentAccessedPerson="PHILIP.STANG"/><access contentAccessed="1/28/2013 2:22:19 PM" contentAccessedPerson="JEAN"/><access contentAccessed="1/29/2013 5:14:00 PM" contentAccessedPerson=""/></page>
	<page id="8114" type="leaf" path="8114.asp" eng="Document Preview Pane (SC003)" fre="Document Preview Pane (SC003)" contentUpdated="1/24/2013 4:48:40 PM" contentUpdatedPerson="" pgCSS="">
		<access contentAccessed="9/28/2012 12:57:33 PM" contentAccessedPerson="JXL811"/>
		<access contentAccessed="1/24/2013 10:44:23 AM" contentAccessedPerson=""/><access contentAccessed="1/24/2013 11:09:19 AM" contentAccessedPerson=""/><access contentAccessed="1/24/2013 1:08:43 PM" contentAccessedPerson="PHILIP.STANG"/><access contentAccessed="1/24/2013 3:59:46 PM" contentAccessedPerson=""/><access contentAccessed="1/24/2013 4:13:29 PM" contentAccessedPerson=""/></page>
	<page id="8115" type="leaf" path="8115.asp" eng="Main File Screen" fre="Main File Screen" contentUpdated="2/6/2013 10:52:57 PM" contentUpdatedPerson="" pgCSS="">
		<access contentAccessed="9/28/2012 12:58:32 PM" contentAccessedPerson="JXL811"/>
		<access contentAccessed="9/28/2012 1:37:23 PM" contentAccessedPerson="JXL811"/>
		<access contentAccessed="11/28/2012 11:35:31 PM" contentAccessedPerson="PHILIP.STANG"/><access contentAccessed="2/6/2013 4:11:32 PM" contentAccessedPerson=""/></page>
	<page id="8116" type="leaf" path="8116.asp" eng="Activity Screen" fre="Activity Screen" contentUpdated="2/8/2013 4:33:24 PM" contentUpdatedPerson="PHILIP.STANG" pgCSS="">
		<access contentAccessed="9/28/2012 1:00:00 PM" contentAccessedPerson="JXL811"/>
		<access contentAccessed="9/28/2012 1:02:42 PM" contentAccessedPerson="JXL811"/>
		<access contentAccessed="9/28/2012 5:21:51 PM" contentAccessedPerson="JXL811"/>
		<access contentAccessed="11/29/2012 12:19:02 AM" contentAccessedPerson="PHILIP.STANG"/><access contentAccessed="2/8/2013 1:46:09 PM" contentAccessedPerson=""/><access contentAccessed="2/8/2013 2:59:01 PM" contentAccessedPerson=""/><access contentAccessed="2/8/2013 2:59:14 PM" contentAccessedPerson=""/><access contentAccessed="2/8/2013 2:59:46 PM" contentAccessedPerson=""/><access contentAccessed="2/8/2013 4:32:59 PM" contentAccessedPerson="PHILIP.STANG"/></page>
	<page id="8118" type="leaf" path="8118.asp" eng="Legal Risk Management Screen" fre="Legal Risk Management Screen"><access contentAccessed="6/4/2013 3:50:25 PM" contentAccessedPerson="CORY"/><access contentAccessed="8/21/2013 9:06:34 AM" contentAccessedPerson=""/></page>
	<page id="8119" type="leaf" path="8119.asp" eng="Opinion Screen" fre="Opinion Screen" contentUpdated="9/28/2012 1:04:59 PM" contentUpdatedPerson="JXL811">
		<access contentAccessed="9/28/2012 1:04:54 PM" contentAccessedPerson="JXL811"/>
	</page>
	<page id="8120" type="leaf" path="8120.asp" eng="File History Screen" fre="File History Screen"/>
	<page id="8121" type="leaf" path="8121.asp" eng="File Properties Screen" fre="File Properties Screen" contentUpdated="11/29/2012 3:55:08 PM" contentUpdatedPerson="PHILIP.STANG">
		<access contentAccessed="9/28/2012 1:06:04 PM" contentAccessedPerson="JXL811"/>
		<access contentAccessed="11/29/2012 3:39:02 PM" contentAccessedPerson="PHILIP.STANG"/><access contentAccessed="11/29/2012 4:11:48 PM" contentAccessedPerson="PHILIP.STANG"/></page>
	<page id="8122" type="leaf" path="8122.asp" eng="Documents (Records) Screen" fre="Documents (Records) Screen" contentUpdated="11/29/2012 3:37:48 PM" contentUpdatedPerson="PHILIP.STANG">
		<access contentAccessed="9/28/2012 1:07:20 PM" contentAccessedPerson="JXL811"/>
		<access contentAccessed="9/28/2012 5:22:14 PM" contentAccessedPerson="JXL811"/>
		<access contentAccessed="11/29/2012 2:30:43 PM" contentAccessedPerson="PHILIP.STANG"/><access contentAccessed="11/29/2012 3:34:59 PM" contentAccessedPerson="PHILIP.STANG"/></page>
	<page id="8123" type="node" path="8123.asp" eng="Atrium Administrator Deskbook" fre="Atrium Administrator Deskbook"/>
	<page id="8124" type="leaf" path="8124.asp" eng="Contacts Screen" fre="Contacts Screen" contentUpdated="11/29/2012 4:17:33 PM" contentUpdatedPerson="PHILIP.STANG">
		<access contentAccessed="9/28/2012 1:09:59 PM" contentAccessedPerson="JXL811"/>
		<access contentAccessed="11/29/2012 4:12:03 PM" contentAccessedPerson="PHILIP.STANG"/></page>
	<page id="8125" type="leaf" path="8125.asp" eng="Offices (associated to file) Screen" fre="Offices (associated to file) Screen"/>
	<page id="8126" type="node" path="8126.asp" eng="Main File Screen and Panes" fre="Main File Screen and Panes"/>
	<page id="8127" type="leaf" path="8127.asp" eng="File Information Pane" fre="File Information Pane" contentUpdated="11/29/2012 12:06:20 AM" contentUpdatedPerson="PHILIP.STANG">
		<access contentAccessed="9/28/2012 1:37:09 PM" contentAccessedPerson="JXL811"/>
		<access contentAccessed="10/1/2012 11:11:00 AM" contentAccessedPerson="JXL811"/><access contentAccessed="11/28/2012 11:39:13 PM" contentAccessedPerson="PHILIP.STANG"/><access contentAccessed="11/28/2012 11:43:38 PM" contentAccessedPerson="PHILIP.STANG"/><access contentAccessed="11/28/2012 11:45:44 PM" contentAccessedPerson="PHILIP.STANG"/><access contentAccessed="11/29/2012 12:02:22 AM" contentAccessedPerson="PHILIP.STANG"/></page>
	<page id="8129" type="node" path="8129.asp" eng="Files and Documents Screens" fre="Files and Documents Screens"/>
	<page id="8130" type="node" path="8130.asp" eng="Office and People-related Screens" fre="Office and People-related Screens"/>
	<page id="8131" type="node" path="8131.asp" eng="Browse and Search" fre="Browse and Search"/>
	<page id="8132" type="node" path="8132.asp" eng="Searching" fre="Searching"/>
	<page id="8133" type="node" path="8133.asp" eng="Browsing" fre="Browsing"/>
	<page id="8134" type="leaf" path="8134.asp" eng="Atrium Explorer" fre="Atrium Explorer"/>
	<page id="8135" type="leaf" path="8135.asp" eng="Office Explorer" fre="Office Explorer"/>
	<page id="8136" type="node" path="8136.asp" eng="Search Results" fre="Search Results"/>
	<page id="8137" type="leaf" path="8137.asp" eng="Personnel Screen" fre="Personnel Screen" contentUpdated="9/28/2012 5:25:57 PM" contentUpdatedPerson="JXL811">
		<access contentAccessed="9/28/2012 5:25:20 PM" contentAccessedPerson="JXL811"/>
	</page>
	<page id="8138" type="leaf" path="8138.asp" eng="Advanced File Search Screen" fre="Advanced File Search Screen" contentUpdated="1/24/2013 10:14:27 PM" contentUpdatedPerson="" pgCSS="">
		<access contentAccessed="9/28/2012 5:28:29 PM" contentAccessedPerson="JXL811"/>
		<access contentAccessed="9/28/2012 5:36:26 PM" contentAccessedPerson="JXL811"/>
		<access contentAccessed="11/29/2012 11:04:19 AM" contentAccessedPerson="PHILIP.STANG"/><access contentAccessed="1/24/2013 10:13:34 PM" contentAccessedPerson=""/></page>
	<page id="8139" type="leaf" path="8139.asp" eng="Advanced Document Search Screen" fre="Advanced Document Search Screen" contentUpdated="1/29/2013 4:31:01 PM" contentUpdatedPerson="" pgCSS=""><access contentAccessed="1/24/2013 10:15:18 PM" contentAccessedPerson=""/><access contentAccessed="1/29/2013 4:29:56 PM" contentAccessedPerson=""/><access contentAccessed="1/29/2013 4:30:31 PM" contentAccessedPerson=""/></page>
	<page id="8140" type="node" path="8140.asp" eng="Help" fre="Help"/>
	<page id="8141" type="node" path="8141.asp" eng="Outlook Browser" fre="Outlook Browser"/>
	<page id="8142" type="leaf" path="8142.asp" eng="Overview (NS002)" fre="Overview" contentUpdated="1/29/2013 4:04:24 PM" contentUpdatedPerson="" pgCSS=""><access contentAccessed="1/24/2013 10:07:32 PM" contentAccessedPerson=""/><access contentAccessed="1/28/2013 9:38:06 AM" contentAccessedPerson=""/><access contentAccessed="1/29/2013 3:27:04 PM" contentAccessedPerson=""/><access contentAccessed="1/29/2013 4:12:50 PM" contentAccessedPerson=""/></page>
	<page id="8143" type="leaf" path="8143.asp" eng="Import Outlook E-mails (NS003)" fre="Import Outlook E-mails (NS003)" contentUpdated="1/29/2013 4:23:39 PM" contentUpdatedPerson="" pgCSS=""><access contentAccessed="1/24/2013 10:08:46 PM" contentAccessedPerson=""/><access contentAccessed="1/29/2013 10:49:41 AM" contentAccessedPerson="PHILIP.STANG"/><access contentAccessed="1/29/2013 11:07:37 AM" contentAccessedPerson="PHILIP.STANG"/><access contentAccessed="1/29/2013 11:23:38 AM" contentAccessedPerson="PHILIP.STANG"/><access contentAccessed="1/29/2013 12:52:57 PM" contentAccessedPerson=""/><access contentAccessed="1/29/2013 1:02:28 PM" contentAccessedPerson=""/><access contentAccessed="1/29/2013 4:13:25 PM" contentAccessedPerson=""/></page>
	<page id="8144" type="leaf" path="8144.asp" eng="Threads and Duplicates (NS004)" fre="Threads and Duplicates (NS004)" contentUpdated="1/29/2013 2:12:30 PM" contentUpdatedPerson="" pgCSS=""><access contentAccessed="1/24/2013 10:09:19 PM" contentAccessedPerson=""/><access contentAccessed="1/29/2013 10:54:08 AM" contentAccessedPerson="PHILIP.STANG"/><access contentAccessed="1/29/2013 1:38:47 PM" contentAccessedPerson=""/></page>
	<page id="8145" type="node" path="8145.asp" eng="Reports Screens" fre="Reports Screens"/>
	<page id="8146" type="node" path="8146.asp" eng="Security Screens" fre="Security Screens"/>
	<page id="8147" type="node" path="8147.asp" eng="Utilities Screens" fre="Utilities Screens"/>
	<page id="8148" type="leaf" path="8148.asp" eng="Reports List Screen" fre="Reports List Screen" contentUpdated="1/29/2013 3:24:14 PM" contentUpdatedPerson="" pgCSS=""><access contentAccessed="1/29/2013 3:23:59 PM" contentAccessedPerson=""/></page>
	<page id="8149" type="leaf" path="8149.asp" eng="Report Viewer Screen" fre="Report Viewer Screen"/>
	<page id="8150" type="leaf" path="8150.asp" eng="File Security Screen" fre="File Security Screen" contentUpdated="1/29/2013 3:23:36 PM" contentUpdatedPerson="" pgCSS=""><access contentAccessed="1/29/2013 3:23:29 PM" contentAccessedPerson=""/></page>
	<page id="8151" type="leaf" path="8151.asp" eng="Officer Security Screen" fre="Officer Security Screen"/>
	<page id="8152" type="leaf" path="8152.asp" eng="Suspended Activities/Auto-Save Screen" fre="Suspended Activities/Auto-Save Screen" contentUpdated="1/29/2013 3:22:42 PM" contentUpdatedPerson="" pgCSS=""><access contentAccessed="12/10/2012 6:52:42 AM" contentAccessedPerson="PHILIP.STANG"/><access contentAccessed="1/29/2013 3:21:58 PM" contentAccessedPerson=""/></page>
	<page id="8153" type="leaf" path="8153.asp" eng="Multi-select List Window" fre="Multi-select List Window" contentUpdated="1/24/2013 10:10:09 PM" contentUpdatedPerson="" pgCSS=""><access contentAccessed="1/24/2013 10:10:05 PM" contentAccessedPerson=""/></page>
	<page id="8154" type="leaf" path="8154.asp" eng="Preferences Screen" fre="Preferences Screen" contentUpdated="1/29/2013 3:21:29 PM" contentUpdatedPerson="" pgCSS=""><access contentAccessed="1/29/2013 3:21:04 PM" contentAccessedPerson=""/></page>
	<page id="8155" type="leaf" path="8155.asp" eng="Timekeeping Screen" fre="Timekeeping Screen"/>
	<page id="8156" type="leaf" path="8156.asp" eng="Login Screen" fre="Login Screen"><access contentAccessed="12/13/2012 7:31:32 PM" contentAccessedPerson="JXL811"/></page>
	<page id="8157" type="leaf" path="8157.asp" eng="Change Password Screen" fre="Change Password Screen"/>
	<page id="8158" type="leaf" path="8158.asp" eng="Batch Review Screen" fre="Batch Review Screen"/>
	<page id="8159" type="leaf" path="8159.asp" eng="Advanced Office Search Screen" fre="Advanced Office Search Screen" contentUpdated="1/29/2013 4:31:20 PM" contentUpdatedPerson="" pgCSS=""><access contentAccessed="1/29/2013 4:31:08 PM" contentAccessedPerson=""/></page>
	<page id="8160" type="leaf" path="8160.asp" eng="Advanced Contact Search Screen" fre="Advanced Contact Search Screen" contentUpdated="1/29/2013 4:33:02 PM" contentUpdatedPerson="" pgCSS=""><access contentAccessed="1/29/2013 4:31:29 PM" contentAccessedPerson=""/><access contentAccessed="1/29/2013 4:31:55 PM" contentAccessedPerson=""/></page>
	<page id="8161" type="leaf" path="8161.asp" eng="Quicksearch - Files and Documents" fre="Quicksearch - Files and Documents" contentUpdated="1/24/2013 10:13:01 PM" contentUpdatedPerson="" pgCSS=""><access contentAccessed="1/24/2013 10:12:56 PM" contentAccessedPerson=""/></page>
	<page id="8162" type="leaf" path="8162.asp" eng="File Search Results Screen" fre="File Search Results Screen" contentUpdated="1/29/2013 4:48:59 PM" contentUpdatedPerson="" pgCSS=""><access contentAccessed="1/24/2013 10:16:08 PM" contentAccessedPerson=""/><access contentAccessed="1/29/2013 4:48:44 PM" contentAccessedPerson=""/></page>
	<page id="8163" type="leaf" path="8163.asp" eng="Document Search Results Screen" fre="Document Search Results Screen" contentUpdated="1/29/2013 4:49:56 PM" contentUpdatedPerson="" pgCSS=""><access contentAccessed="1/24/2013 10:16:41 PM" contentAccessedPerson=""/><access contentAccessed="1/29/2013 4:49:26 PM" contentAccessedPerson=""/></page>
	<page id="8165" type="node" path="8165.asp" eng="Videos" fre="Videos"/><page id="8166" type="leaf" path="8166.asp" eng="Receipt of IE Appeals to the General Division (GE01)" fre="Receipt of IE Appeals to the General Division (GE01)" contentUpdated="12/6/2012 2:53:40 PM" contentUpdatedPerson="PHILIP.STANG"><access contentAccessed="10/1/2012 1:51:21 PM" contentAccessedPerson="JXL811"/><access contentAccessed="10/1/2012 7:14:37 PM" contentAccessedPerson="JXL811"/><access contentAccessed="10/2/2012 9:10:16 AM" contentAccessedPerson="JXL811"/><access contentAccessed="10/2/2012 11:09:28 AM" contentAccessedPerson="JXL811"/><access contentAccessed="10/2/2012 8:40:00 PM" contentAccessedPerson="JXL811"/><access contentAccessed="10/2/2012 8:40:58 PM" contentAccessedPerson="JXL811"/><access contentAccessed="10/2/2012 8:46:05 PM" contentAccessedPerson="JXL811"/><access contentAccessed="10/2/2012 8:48:06 PM" contentAccessedPerson="JXL811"/><access contentAccessed="10/2/2012 8:49:05 PM" contentAccessedPerson="JXL811"/><access contentAccessed="10/2/2012 10:44:57 PM" contentAccessedPerson="JXL811"/><access contentAccessed="10/2/2012 10:46:06 PM" contentAccessedPerson="JXL811"/><access contentAccessed="10/2/2012 10:55:39 PM" contentAccessedPerson="JXL811"/><access contentAccessed="10/5/2012 5:16:45 PM" contentAccessedPerson="JXL811"/><access contentAccessed="11/21/2012 11:01:23 AM" contentAccessedPerson="PHILIP.STANG"/><access contentAccessed="11/21/2012 11:52:13 AM" contentAccessedPerson="PHILIP.STANG"/><access contentAccessed="11/29/2012 10:56:24 AM" contentAccessedPerson="PHILIP.STANG"/><access contentAccessed="11/29/2012 10:58:11 AM" contentAccessedPerson="PHILIP.STANG"/><access contentAccessed="11/29/2012 10:59:34 AM" contentAccessedPerson="PHILIP.STANG"/><access contentAccessed="11/29/2012 3:40:51 PM" contentAccessedPerson="PHILIP.STANG"/><access contentAccessed="11/29/2012 3:54:17 PM" contentAccessedPerson="PHILIP.STANG"/><access contentAccessed="11/30/2012 10:45:39 AM" contentAccessedPerson="PHILIP.STANG"/><access contentAccessed="11/30/2012 11:40:15 AM" contentAccessedPerson="PHILIP.STANG"/><access contentAccessed="12/3/2012 9:44:06 AM" contentAccessedPerson="PHILIP.STANG"/><access contentAccessed="12/3/2012 11:17:57 AM" contentAccessedPerson="PHILIP.STANG"/><access contentAccessed="12/4/2012 1:38:44 PM" contentAccessedPerson="PHILIP.STANG"/><access contentAccessed="12/4/2012 2:54:41 PM" contentAccessedPerson="PHILIP.STANG"/><access contentAccessed="12/4/2012 3:30:20 PM" contentAccessedPerson="PHILIP.STANG"/><access contentAccessed="12/5/2012 9:53:49 AM" contentAccessedPerson="PHILIP.STANG"/><access contentAccessed="12/5/2012 10:47:10 AM" contentAccessedPerson="PHILIP.STANG"/><access contentAccessed="12/5/2012 11:41:08 AM" contentAccessedPerson="PHILIP.STANG"/><access contentAccessed="12/5/2012 1:17:07 PM" contentAccessedPerson="PHILIP.STANG"/><access contentAccessed="12/5/2012 1:38:48 PM" contentAccessedPerson="PHILIP.STANG"/><access contentAccessed="12/5/2012 2:02:28 PM" contentAccessedPerson="PHILIP.STANG"/><access contentAccessed="12/5/2012 2:03:43 PM" contentAccessedPerson="PHILIP.STANG"/><access contentAccessed="12/5/2012 2:06:32 PM" contentAccessedPerson="PHILIP.STANG"/><access contentAccessed="12/5/2012 8:15:02 PM" contentAccessedPerson="PHILIP.STANG"/><access contentAccessed="12/5/2012 8:33:35 PM" contentAccessedPerson="PHILIP.STANG"/><access contentAccessed="12/6/2012 10:26:48 AM" contentAccessedPerson="PHILIP.STANG"/><access contentAccessed="12/6/2012 2:40:45 PM" contentAccessedPerson="PHILIP.STANG"/><access contentAccessed="1/9/2013 2:29:00 PM" contentAccessedPerson="JEAN"/><access contentAccessed="1/9/2013 2:53:17 PM" contentAccessedPerson="CORY"/><access contentAccessed="7/9/2013 1:39:06 PM" contentAccessedPerson="JEAN"/></page><page id="8167" type="leaf" path="8167.asp" eng="Processing of EI Appeal to General Division (GE02)" fre="Processing of EI Appeal to General Division (GE02)" contentUpdated="12/6/2012 2:40:37 PM" contentUpdatedPerson="PHILIP.STANG"><access contentAccessed="10/2/2012 8:52:54 PM" contentAccessedPerson="JXL811"/><access contentAccessed="10/5/2012 5:19:29 PM" contentAccessedPerson="JXL811"/><access contentAccessed="12/5/2012 8:14:50 PM" contentAccessedPerson="PHILIP.STANG"/><access contentAccessed="12/5/2012 8:15:22 PM" contentAccessedPerson="PHILIP.STANG"/><access contentAccessed="12/5/2012 11:20:04 PM" contentAccessedPerson="PHILIP.STANG"/><access contentAccessed="12/6/2012 8:56:12 AM" contentAccessedPerson="PHILIP.STANG"/><access contentAccessed="12/6/2012 9:38:21 AM" contentAccessedPerson="PHILIP.STANG"/><access contentAccessed="12/6/2012 10:26:27 AM" contentAccessedPerson="PHILIP.STANG"/><access contentAccessed="12/6/2012 10:27:08 AM" contentAccessedPerson="PHILIP.STANG"/><access contentAccessed="12/6/2012 11:11:15 AM" contentAccessedPerson="PHILIP.STANG"/><access contentAccessed="12/6/2012 1:47:03 PM" contentAccessedPerson="PHILIP.STANG"/><access contentAccessed="12/6/2012 2:40:32 PM" contentAccessedPerson="PHILIP.STANG"/><access contentAccessed="12/7/2012 6:01:03 PM" contentAccessedPerson="PHILIP.STANG"/></page><page id="8168" type="node" path="8168.asp" eng="Registrar's Deskbook" fre="Registrar's Deskbook"/><page id="8169" type="leaf" path="8169.asp" eng="Office Search Results Screen" fre="Office Search Results Screen"/><page id="8170" type="leaf" path="8170.asp" eng="Contact Search Results Screen" fre="Contact Search Results Screen"/><page id="8171" type="leaf" path="8171.asp" eng="File Assembly Checklist Process (GE03)" fre="File Assembly Checklist Process (GE03)"/><page id="8172" type="leaf" path="8172.asp" eng="Case Assessment Process (GE04)" fre="Case Assessment Process (GE04)"/><page id="8173" type="leaf" path="8173.asp" eng="Late Filing of Appeal (more than one year) Process (GE05)" fre="Late Filing of Appeal (more than one year) Process (GE05)"/><page id="8174" type="leaf" path="8174.asp" eng="Summary Dismissal Process (GE06)" fre="Summary Dismissal Process (GE06)"/><page id="8175" type="leaf" path="8175.asp" eng="Initial Hearing Scheduling Process (GE07)" fre="Initial Hearing Scheduling Process (GE07)"/><page id="8176" type="leaf" path="8176.asp" eng="Dispute Resolution Process (GE08)" fre="Dispute Resolution Process (GE08)"/><page id="8177" type="leaf" path="8177.asp" eng="Hearing Process (GE09)" fre="Hearing Process (GE09)"/><page id="8178" type="leaf" path="8178.asp" eng="Introduction" fre="Introduction" contentUpdated="11/21/2012 11:49:10 AM" contentUpdatedPerson="PHILIP.STANG"><access contentAccessed="10/1/2012 1:33:47 PM" contentAccessedPerson="JXL811"/><access contentAccessed="10/1/2012 1:34:21 PM" contentAccessedPerson="JXL811"/><access contentAccessed="10/1/2012 1:43:26 PM" contentAccessedPerson="JXL811"/><access contentAccessed="11/21/2012 11:33:55 AM" contentAccessedPerson="PHILIP.STANG"/><access contentAccessed="11/24/2012 2:55:06 PM" contentAccessedPerson="PHILIP.STANG"/></page><page id="8179" type="leaf" path="8179.asp" eng="Introduction" fre="Introduction"/><page id="8180" type="leaf" path="8180.asp" eng="Introduction" fre="Introduction"><access contentAccessed="1/7/2013 3:00:09 PM" contentAccessedPerson=""/><access contentAccessed="1/8/2013 10:52:04 PM" contentAccessedPerson=""/><access contentAccessed="1/9/2013 2:39:08 PM" contentAccessedPerson="CORY"/></page><page id="8181" type="leaf" path="8181.asp" eng="Site Map" fre="Carte du site" contentUpdated="10/1/2012 1:57:44 PM" contentUpdatedPerson="JXL811"><access contentAccessed="10/1/2012 1:54:38 PM" contentAccessedPerson="JXL811"/><access contentAccessed="10/1/2012 1:56:28 PM" contentAccessedPerson="JXL811"/><access contentAccessed="12/13/2012 7:31:48 PM" contentAccessedPerson="JXL811"/></page><page id="8182" type="node" path="8182.asp" eng="Knowledge Centre" fre="Centre de connaissance"/><page id="8183" type="node" path="8183.asp" eng="Legislation" fre="Legislation"/><page id="8184" type="node" path="8184.asp" eng="Subject-based (Not Founded on Legislation)" fre="Subject-based (Not Founded on Legislation)"/><page id="8186" type="node" path="8186.asp" eng="Federal" fre="Fédérale"/><page id="8187" type="node" path="8187.asp" eng="Provincial" fre="Provincial"/><page id="8188" type="node" path="8188.asp" eng="International" fre="International"/><page id="8189" type="node" path="8189.asp" eng="Employment Insurance Act (S.C. 1986, c.23)" fre="Loi sur l'assurance d'emploi (L.C. 1986, ch.23)"/><page id="8190" type="node" path="8190.asp" eng="Canada Pension Plan (R.S.C. 1985, c. C-8)" fre="Régime du pension du Canada (L.R.C. 1985, c. C-8)"/><page id="8193" type="leaf" path="8193.asp" eng="10(4)  (Antedate - Late Initial Claims)" fre="10(4)  (Antidatation : demande initiale tardive )" contentUpdated="5/22/2013 11:41:37 AM" contentUpdatedPerson="CORY" pgCSS=""><access contentAccessed="11/1/2012 10:32:36 AM" contentAccessedPerson="PHILIP.STANG"/><access contentAccessed="11/1/2012 10:35:23 AM" contentAccessedPerson="JXL811"/><access contentAccessed="11/1/2012 10:44:13 AM" contentAccessedPerson="PHILIP.STANG"/><access contentAccessed="11/1/2012 11:32:14 AM" contentAccessedPerson="PHILIP.STANG"/><access contentAccessed="11/1/2012 11:33:39 AM" contentAccessedPerson="PHILIP.STANG"/><access contentAccessed="11/1/2012 1:40:34 PM" contentAccessedPerson="PHILIP.STANG"/><access contentAccessed="11/28/2012 10:14:22 AM" contentAccessedPerson="JXL811"/><access contentAccessed="11/28/2012 5:04:31 PM" contentAccessedPerson="PHILIP.STANG"/><access contentAccessed="11/28/2012 5:46:37 PM" contentAccessedPerson="PHILIP.STANG"/><access contentAccessed="5/1/2013 12:23:48 PM" contentAccessedPerson="CORY"/><access contentAccessed="5/1/2013 12:27:08 PM" contentAccessedPerson="CORY"/><access contentAccessed="5/1/2013 12:36:56 PM" contentAccessedPerson="CORY"/><access contentAccessed="5/2/2013 9:34:48 AM" contentAccessedPerson="CORY"/><access contentAccessed="5/2/2013 10:48:49 AM" contentAccessedPerson="CORY"/><access contentAccessed="5/2/2013 1:23:54 PM" contentAccessedPerson="CORY"/><access contentAccessed="5/2/2013 3:11:15 PM" contentAccessedPerson="CORY"/><access contentAccessed="5/2/2013 3:17:30 PM" contentAccessedPerson="CORY"/><access contentAccessed="5/2/2013 3:27:52 PM" contentAccessedPerson="CORY"/><access contentAccessed="5/2/2013 3:32:21 PM" contentAccessedPerson="CORY"/><access contentAccessed="5/2/2013 3:33:51 PM" contentAccessedPerson="CORY"/><access contentAccessed="5/6/2013 9:13:40 AM" contentAccessedPerson="JEAN"/><access contentAccessed="5/6/2013 4:50:29 PM" contentAccessedPerson="CORY"/><access contentAccessed="5/6/2013 5:02:08 PM" contentAccessedPerson="CORY"/><access contentAccessed="5/7/2013 8:22:32 AM" contentAccessedPerson="CORY"/><access contentAccessed="5/10/2013 12:33:07 PM" contentAccessedPerson="CORY"/><access contentAccessed="5/13/2013 8:29:03 AM" contentAccessedPerson="CORY"/><access contentAccessed="5/13/2013 9:18:14 AM" contentAccessedPerson="CORY"/><access contentAccessed="5/13/2013 9:21:30 AM" contentAccessedPerson="CORY"/><access contentAccessed="5/13/2013 9:24:28 AM" contentAccessedPerson="CORY"/><access contentAccessed="5/13/2013 12:44:33 PM" contentAccessedPerson="CORY"/><access contentAccessed="5/13/2013 12:44:46 PM" contentAccessedPerson="CORY"/><access contentAccessed="5/13/2013 12:44:56 PM" contentAccessedPerson="CORY"/><access contentAccessed="5/13/2013 12:45:26 PM" contentAccessedPerson="CORY"/><access contentAccessed="5/13/2013 12:49:04 PM" contentAccessedPerson="CORY"/><access contentAccessed="5/13/2013 1:00:51 PM" contentAccessedPerson="CORY"/><access contentAccessed="5/13/2013 1:11:22 PM" contentAccessedPerson="CORY"/><access contentAccessed="5/13/2013 2:45:31 PM" contentAccessedPerson="CORY"/><access contentAccessed="5/16/2013 11:16:58 AM" contentAccessedPerson=""/><access contentAccessed="5/16/2013 11:17:04 AM" contentAccessedPerson=""/><access contentAccessed="5/16/2013 11:17:14 AM" contentAccessedPerson=""/><access contentAccessed="5/16/2013 11:17:30 AM" contentAccessedPerson=""/><access contentAccessed="5/16/2013 11:17:35 AM" contentAccessedPerson=""/><access contentAccessed="5/16/2013 11:17:58 AM" contentAccessedPerson=""/><access contentAccessed="5/16/2013 11:18:15 AM" contentAccessedPerson=""/><access contentAccessed="5/16/2013 11:18:44 AM" contentAccessedPerson=""/><access contentAccessed="5/16/2013 7:25:42 PM" contentAccessedPerson="CORY"/><access contentAccessed="5/16/2013 7:32:38 PM" contentAccessedPerson="CORY"/><access contentAccessed="5/17/2013 3:11:12 PM" contentAccessedPerson=""/><access contentAccessed="5/17/2013 3:11:52 PM" contentAccessedPerson=""/><access contentAccessed="5/17/2013 3:11:56 PM" contentAccessedPerson=""/><access contentAccessed="5/17/2013 3:11:58 PM" contentAccessedPerson=""/><access contentAccessed="5/22/2013 10:30:29 AM" contentAccessedPerson="CORY"/><access contentAccessed="5/22/2013 10:30:32 AM" contentAccessedPerson="CORY"/><access contentAccessed="5/22/2013 10:33:00 AM" contentAccessedPerson="CORY"/><access contentAccessed="5/22/2013 10:35:11 AM" contentAccessedPerson="CORY"/><access contentAccessed="5/22/2013 11:31:44 AM" contentAccessedPerson="CORY"/><access contentAccessed="5/22/2013 11:38:38 AM" contentAccessedPerson="CORY"/><access contentAccessed="5/22/2013 11:40:54 AM" contentAccessedPerson="CORY"/><access contentAccessed="5/22/2013 11:40:57 AM" contentAccessedPerson="CORY"/><access contentAccessed="6/1/2013 9:47:56 AM" contentAccessedPerson="CORY"/></page><page id="8194" type="node" path="8194.asp" eng="Old Age Security Act (R.S.C. 1985, c. O-9)" fre="Old Age Security Act (L.R.C. 1985, ch. O-9)"/><page id="8195" type="node" path="8195.asp" eng="Alberta" fre="Alberta"/><page id="8196" type="node" path="8196.asp" eng="British Columbia" fre="Columbia-britannique"/><page id="8197" type="node" path="8197.asp" eng="Manitoba" fre="Manitoba"/><page id="8198" type="leaf" path="8198.asp" eng="File Important Message Pane" fre="File Important Message Pane" contentUpdated="2/8/2013 1:45:12 PM" contentUpdatedPerson="" pgCSS=""><access contentAccessed="11/29/2012 12:10:49 AM" contentAccessedPerson="PHILIP.STANG"/><access contentAccessed="2/8/2013 9:56:08 AM" contentAccessedPerson=""/><access contentAccessed="2/8/2013 12:44:35 PM" contentAccessedPerson=""/></page><page id="8199" type="leaf" path="8199.asp" eng="BF List Pane (SC004)" fre="BF List Pane (SC004)" contentUpdated="1/30/2013 9:48:45 AM" contentUpdatedPerson="PHILIP.STANG" pgCSS=""><access contentAccessed="1/24/2013 6:56:38 PM" contentAccessedPerson=""/><access contentAccessed="1/28/2013 2:17:18 PM" contentAccessedPerson="JEAN"/><access contentAccessed="1/29/2013 5:28:32 PM" contentAccessedPerson="PHILIP.STANG"/><access contentAccessed="1/30/2013 9:10:46 AM" contentAccessedPerson="PHILIP.STANG"/><access contentAccessed="2/6/2013 1:37:50 PM" contentAccessedPerson=""/></page><page id="8200" type="node" path="8200.asp" eng="Income Tax Act (R.S.C. 1985, c.1 (5th Supp.))" fre="Loi sur l'impôt (L.R.C. 1985, ch.1 (5e supp.))"/><page id="8201" type="leaf" path="8201.asp" eng="Index (Alphabetical Order)" fre="Index (Ordre alphabetic)" contentUpdated="6/3/2013 8:42:13 AM" contentUpdatedPerson="CORY" pgCSS=""><access contentAccessed="11/24/2012 2:53:21 PM" contentAccessedPerson="PHILIP.STANG"/><access contentAccessed="11/24/2012 2:55:46 PM" contentAccessedPerson="PHILIP.STANG"/><access contentAccessed="11/24/2012 2:57:28 PM" contentAccessedPerson="PHILIP.STANG"/><access contentAccessed="11/24/2012 2:58:49 PM" contentAccessedPerson="PHILIP.STANG"/><access contentAccessed="11/26/2012 3:25:57 PM" contentAccessedPerson="PHILIP.STANG"/><access contentAccessed="6/3/2013 8:40:22 AM" contentAccessedPerson="CORY"/></page><page id="8202" type="leaf" path="8202.asp" eng="Processes" fre="Processes" contentUpdated="11/26/2012 3:25:36 PM" contentUpdatedPerson="PHILIP.STANG"><access contentAccessed="11/26/2012 3:24:19 PM" contentAccessedPerson="PHILIP.STANG"/></page><page id="8204" type="leaf" path="8204.asp" eng="10(5) (Antedate - Other Late Claims)" fre="10(5) (Antidatation : autres demandes tardives)" contentUpdated="5/17/2013 2:47:11 PM" contentUpdatedPerson="CORY" pgCSS=""><access contentAccessed="11/28/2012 5:09:56 PM" contentAccessedPerson="PHILIP.STANG"/><access contentAccessed="11/28/2012 5:58:08 PM" contentAccessedPerson="PHILIP.STANG"/><access contentAccessed="12/13/2012 7:32:01 PM" contentAccessedPerson="JXL811"/><access contentAccessed="5/2/2013 3:22:51 PM" contentAccessedPerson="CORY"/><access contentAccessed="5/2/2013 3:28:29 PM" contentAccessedPerson="CORY"/><access contentAccessed="5/2/2013 3:34:31 PM" contentAccessedPerson="CORY"/><access contentAccessed="5/2/2013 3:37:24 PM" contentAccessedPerson="CORY"/><access contentAccessed="5/2/2013 3:49:55 PM" contentAccessedPerson="CORY"/><access contentAccessed="5/2/2013 3:54:32 PM" contentAccessedPerson="CORY"/><access contentAccessed="5/2/2013 4:27:01 PM" contentAccessedPerson="CORY"/><access contentAccessed="5/2/2013 4:30:57 PM" contentAccessedPerson="CORY"/><access contentAccessed="5/6/2013 9:14:13 AM" contentAccessedPerson="JEAN"/><access contentAccessed="5/13/2013 9:25:03 AM" contentAccessedPerson="CORY"/><access contentAccessed="5/13/2013 9:25:26 AM" contentAccessedPerson="CORY"/><access contentAccessed="5/13/2013 12:34:59 PM" contentAccessedPerson="CORY"/><access contentAccessed="5/13/2013 12:35:13 PM" contentAccessedPerson="CORY"/><access contentAccessed="5/13/2013 12:49:51 PM" contentAccessedPerson="CORY"/><access contentAccessed="5/13/2013 12:51:19 PM" contentAccessedPerson="CORY"/><access contentAccessed="5/13/2013 12:51:33 PM" contentAccessedPerson="CORY"/><access contentAccessed="5/13/2013 12:52:47 PM" contentAccessedPerson="CORY"/><access contentAccessed="5/13/2013 12:52:50 PM" contentAccessedPerson="CORY"/><access contentAccessed="5/16/2013 8:44:17 PM" contentAccessedPerson="CORY"/><access contentAccessed="5/16/2013 8:44:21 PM" contentAccessedPerson="CORY"/><access contentAccessed="5/16/2013 8:46:51 PM" contentAccessedPerson="CORY"/><access contentAccessed="5/16/2013 8:46:56 PM" contentAccessedPerson="CORY"/><access contentAccessed="5/16/2013 9:13:27 PM" contentAccessedPerson=""/><access contentAccessed="5/16/2013 9:13:33 PM" contentAccessedPerson=""/><access contentAccessed="5/17/2013 2:44:28 PM" contentAccessedPerson="CORY"/><access contentAccessed="5/17/2013 2:44:37 PM" contentAccessedPerson="CORY"/><access contentAccessed="5/22/2013 11:39:20 AM" contentAccessedPerson="CORY"/><access contentAccessed="5/31/2013 9:09:48 AM" contentAccessedPerson="CORY"/></page><page id="8205" type="node" path="8205.asp" eng="Business Line-related Screens" fre="Business Line-related Screens"/><page id="8206" type="node" path="8206.asp" eng="Appeals to the Social Security Tribunal (SST)" fre="Appeals to the Social Security Tribunal (SST)"/><page id="8207" type="leaf" path="8207.asp" eng="Appeal Screen" fre="Appeal Screen"/><page id="8208" type="leaf" path="8208.asp" eng="Matters Screen" fre="Matters Screen"/><page id="8209" type="leaf" path="8209.asp" eng="Other ..." fre="Other ..."/><page id="8210" type="node" path="8210.asp" eng="Legal Advisory" fre="Legal Advisory"/><page id="8211" type="leaf" path="8211.asp" eng="Legal Risk Management Screen" fre=""/><page id="8212" type="leaf" path="8212.asp" eng="Opinion Screen" fre="Opinion Screen" contentUpdated="1/29/2013 2:48:34 PM" contentUpdatedPerson="" pgCSS=""><access contentAccessed="1/29/2013 2:48:13 PM" contentAccessedPerson=""/></page><page id="8213" type="node" path="8213.asp" eng="Medical Advisory" fre="Medical Advisory"/><page id="8214" type="leaf" path="8214.asp" eng="Medical Opinions" fre="Medical Opinions"/><page id="8215" type="leaf" path="8215.asp" eng="Index (Alphabetical Order)" fre="Index (Alphabetical Order)" contentUpdated="1/5/2013 10:17:36 AM" contentUpdatedPerson="PHILIP.STANG"><access contentAccessed="12/10/2012 8:34:39 AM" contentAccessedPerson="PHILIP.STANG"/><access contentAccessed="1/5/2013 9:33:09 AM" contentAccessedPerson="PHILIP.STANG"/><access contentAccessed="1/5/2013 10:14:17 AM" contentAccessedPerson="PHILIP.STANG"/></page><page id="8216" type="leaf" path="8216.asp" eng="Training Outline" fre="Training Outline" contentUpdated="2/20/2013 5:09:01 PM" contentUpdatedPerson="" pgCSS=""><access contentAccessed="12/2/2012 11:40:18 AM" contentAccessedPerson="PHILIP.STANG"/><access contentAccessed="2/20/2013 4:42:55 PM" contentAccessedPerson=""/></page><page id="8217" type="leaf" path="8217.asp" eng="Late Filing of Appeal (more than 30 days, less than 1 year) Process (GE16)" fre="Late Filing of Appeal (more than 30 days, less than 1 year) Process (GE16)"/><page id="8218" type="leaf" path="8218.asp" eng="... add a Contact to a file" fre="... add a Contact to a file" contentUpdated="1/5/2013 9:57:34 AM" contentUpdatedPerson="PHILIP.STANG"><access contentAccessed="12/17/2012 10:05:03 AM" contentAccessedPerson="PHILIP.STANG"/><access contentAccessed="1/5/2013 9:20:23 AM" contentAccessedPerson="PHILIP.STANG"/><access contentAccessed="1/5/2013 9:48:24 AM" contentAccessedPerson="PHILIP.STANG"/></page><page id="8219" type="leaf" path="8219.asp" eng="... add an Office to a file" fre="... add an Office to a file" contentUpdated="1/5/2013 10:09:55 AM" contentUpdatedPerson="PHILIP.STANG"><access contentAccessed="1/5/2013 9:43:19 AM" contentAccessedPerson="PHILIP.STANG"/></page><page id="8220" type="leaf" path="8220.asp" eng="... associate a contact with an office" fre="... associate a contact with an office" contentUpdated="1/5/2013 10:18:26 AM" contentUpdatedPerson="PHILIP.STANG"><access contentAccessed="1/5/2013 10:18:09 AM" contentAccessedPerson="PHILIP.STANG"/></page><page id="8221" type="leaf" path="8221.asp" eng="... attach a link to a draft document" fre="... attach a link to a draft document" contentUpdated="1/5/2013 10:19:50 AM" contentUpdatedPerson="PHILIP.STANG"><access contentAccessed="1/5/2013 10:19:35 AM" contentAccessedPerson="PHILIP.STANG"/></page><page id="8222" type="leaf" path="8222.asp" eng="... attach a document from and external drive" fre="... attach a document from and external drive"/><page id="8223" type="leaf" path="8223.asp" eng="... add a BF to a file" fre="... add a BF to a file" contentUpdated="12/10/2012 7:13:01 AM" contentUpdatedPerson="PHILIP.STANG"><access contentAccessed="12/10/2012 5:59:45 AM" contentAccessedPerson="PHILIP.STANG"/><access contentAccessed="12/10/2012 6:11:27 AM" contentAccessedPerson="PHILIP.STANG"/><access contentAccessed="12/10/2012 7:06:02 AM" contentAccessedPerson="PHILIP.STANG"/><access contentAccessed="12/10/2012 7:08:11 AM" contentAccessedPerson="PHILIP.STANG"/><access contentAccessed="12/10/2012 7:10:21 AM" contentAccessedPerson="PHILIP.STANG"/><access contentAccessed="12/17/2012 10:04:50 AM" contentAccessedPerson="PHILIP.STANG"/></page><page id="8224" type="leaf" path="8224.asp" eng="... modify a BF" fre="... modify a BF" contentUpdated="12/10/2012 7:24:39 AM" contentUpdatedPerson="PHILIP.STANG"><access contentAccessed="12/10/2012 7:13:28 AM" contentAccessedPerson="PHILIP.STANG"/></page><page id="8226" type="leaf" path="8226.asp" eng="... browse (drill down) files and other &quot;trees&quot;" fre="... browse (drill down) files and other &quot;trees&quot;" contentUpdated="1/5/2013 10:21:21 AM" contentUpdatedPerson="PHILIP.STANG"><access contentAccessed="1/5/2013 10:21:12 AM" contentAccessedPerson="PHILIP.STANG"/><access contentAccessed="1/5/2013 10:21:55 AM" contentAccessedPerson="PHILIP.STANG"/></page><page id="8227" type="leaf" path="8227.asp" eng="... check out-in a (draft) document" fre="... check out-in a (draft) document" contentUpdated="1/5/2013 10:22:51 AM" contentUpdatedPerson="PHILIP.STANG"><access contentAccessed="1/5/2013 10:22:23 AM" contentAccessedPerson="PHILIP.STANG"/></page><page id="8228" type="leaf" path="8228.asp" eng="... complete / uncomplete a BF" fre="... complete / uncomplete a BF" contentUpdated="1/3/2013 2:20:20 PM" contentUpdatedPerson="PHILIP.STANG"><access contentAccessed="12/10/2012 7:25:20 AM" contentAccessedPerson="PHILIP.STANG"/><access contentAccessed="1/3/2013 10:18:42 AM" contentAccessedPerson="PHILIP.STANG"/><access contentAccessed="1/3/2013 10:53:47 AM" contentAccessedPerson="PHILIP.STANG"/><access contentAccessed="1/3/2013 11:54:24 AM" contentAccessedPerson="PHILIP.STANG"/><access contentAccessed="1/3/2013 1:10:47 PM" contentAccessedPerson="PHILIP.STANG"/><access contentAccessed="1/3/2013 2:20:13 PM" contentAccessedPerson="PHILIP.STANG"/></page><page id="8229" type="leaf" path="8229.asp" eng="... copy a document" fre="... copy a document" contentUpdated="1/5/2013 10:23:41 AM" contentUpdatedPerson="PHILIP.STANG"><access contentAccessed="1/5/2013 10:23:22 AM" contentAccessedPerson="PHILIP.STANG"/></page><page id="8230" type="leaf" path="8230.asp" eng="... create a new e-mail" fre="... create a new e-mail"/><page id="8231" type="leaf" path="8231.asp" eng="... create a shortcut" fre="" contentUpdated="1/5/2013 10:26:30 AM" contentUpdatedPerson="PHILIP.STANG"><access contentAccessed="1/5/2013 10:24:11 AM" contentAccessedPerson="PHILIP.STANG"/><access contentAccessed="1/5/2013 10:25:59 AM" contentAccessedPerson="PHILIP.STANG"/></page><page id="8232" type="leaf" path="8232.asp" eng="... cross-reference a file" fre="... cross-reference a file" contentUpdated="1/5/2013 10:27:20 AM" contentUpdatedPerson="PHILIP.STANG"><access contentAccessed="1/5/2013 10:26:52 AM" contentAccessedPerson="PHILIP.STANG"/></page><page id="8233" type="leaf" path="8233.asp" eng="... delete an activity" fre="... delete an activity" contentUpdated="1/5/2013 10:29:40 AM" contentUpdatedPerson="PHILIP.STANG"><access contentAccessed="1/5/2013 10:28:11 AM" contentAccessedPerson="PHILIP.STANG"/></page><page id="8234" type="leaf" path="8234.asp" eng="... enter an activity" fre="... enter an activity" contentUpdated="1/5/2013 10:30:37 AM" contentUpdatedPerson="PHILIP.STANG"><access contentAccessed="1/5/2013 10:30:20 AM" contentAccessedPerson="PHILIP.STANG"/></page><page id="8235" type="leaf" path="8235.asp" eng="... import an Outlook e-mail" fre="... import an Outlook e-mail" contentUpdated="1/5/2013 10:31:49 AM" contentUpdatedPerson="PHILIP.STANG"><access contentAccessed="1/5/2013 10:31:41 AM" contentAccessedPerson="PHILIP.STANG"/></page><page id="8236" type="leaf" path="8236.asp" eng="... mark/unmark an e-mail as read" fre="... mark/unmark an e-mail as read"/><page id="8237" type="leaf" path="8237.asp" eng="... move an activity" fre="... move an activity" contentUpdated="1/5/2013 10:35:47 AM" contentUpdatedPerson="PHILIP.STANG"><access contentAccessed="1/5/2013 10:33:03 AM" contentAccessedPerson="PHILIP.STANG"/></page><page id="8238" type="leaf" path="8238.asp" eng="... remove a contact from a file" fre="... remove a contact from a file" contentUpdated="1/5/2013 10:34:33 AM" contentUpdatedPerson="PHILIP.STANG"><access contentAccessed="1/5/2013 10:34:13 AM" contentAccessedPerson="PHILIP.STANG"/></page><page id="8239" type="leaf" path="8239.asp" eng="... remove an office from a file" fre="... remove an office from a file" contentUpdated="1/5/2013 10:36:14 AM" contentUpdatedPerson="PHILIP.STANG"><access contentAccessed="1/5/2013 10:36:02 AM" contentAccessedPerson="PHILIP.STANG"/></page><page id="8240" type="leaf" path="8240.asp" eng="... revise a draft" fre="... revise a draft" contentUpdated="1/5/2013 10:37:05 AM" contentUpdatedPerson="PHILIP.STANG"><access contentAccessed="1/5/2013 10:36:46 AM" contentAccessedPerson="PHILIP.STANG"/></page><page id="8241" type="leaf" path="8241.asp" eng="... upload (import) a single document" fre="... upload (import) a single document" contentUpdated="1/5/2013 10:38:41 AM" contentUpdatedPerson="PHILIP.STANG"><access contentAccessed="1/5/2013 10:37:52 AM" contentAccessedPerson="PHILIP.STANG"/></page><page id="8242" type="leaf" path="8242.asp" eng="... upload (import) multiple documents" fre="... upload (import) multiple documents" contentUpdated="1/5/2013 10:39:24 AM" contentUpdatedPerson="PHILIP.STANG"><access contentAccessed="1/5/2013 10:39:08 AM" contentAccessedPerson="PHILIP.STANG"/></page><page id="8243" type="leaf" path="8243.asp" eng="... use grids" fre="... use grids"/><page id="8245" type="leaf" path="8245.asp" eng="... work as someone else" fre="... work as someone else" contentUpdated="1/5/2013 10:40:38 AM" contentUpdatedPerson="PHILIP.STANG"><access contentAccessed="1/5/2013 10:40:18 AM" contentAccessedPerson="PHILIP.STANG"/></page><page id="8246" type="leaf" path="8246.asp" eng="... save (suspend) an activity as a draft" fre="... save (suspend) an activity as a draft" contentUpdated="12/10/2012 7:03:40 AM" contentUpdatedPerson="PHILIP.STANG"><access contentAccessed="12/10/2012 5:22:52 AM" contentAccessedPerson="PHILIP.STANG"/><access contentAccessed="12/10/2012 5:26:51 AM" contentAccessedPerson="PHILIP.STANG"/><access contentAccessed="12/10/2012 5:51:59 AM" contentAccessedPerson="PHILIP.STANG"/><access contentAccessed="12/10/2012 6:22:52 AM" contentAccessedPerson="PHILIP.STANG"/><access contentAccessed="12/10/2012 6:57:37 AM" contentAccessedPerson="PHILIP.STANG"/></page><page id="8247" type="leaf" path="8247.asp" eng="... resume / recover an activity" fre="... resume / recover an activity" contentUpdated="12/10/2012 6:55:35 AM" contentUpdatedPerson="PHILIP.STANG"><access contentAccessed="12/10/2012 5:32:52 AM" contentAccessedPerson="PHILIP.STANG"/><access contentAccessed="12/10/2012 5:39:07 AM" contentAccessedPerson="PHILIP.STANG"/><access contentAccessed="12/10/2012 6:23:06 AM" contentAccessedPerson="PHILIP.STANG"/><access contentAccessed="12/10/2012 6:54:43 AM" contentAccessedPerson="PHILIP.STANG"/></page><page id="8248" type="leaf" path="8248.asp" eng="... delete a BF" fre="... delete a BF" contentUpdated="12/10/2012 8:07:13 AM" contentUpdatedPerson="PHILIP.STANG"><access contentAccessed="12/10/2012 7:59:12 AM" contentAccessedPerson="PHILIP.STANG"/></page><page id="8249" type="leaf" path="8249.asp" eng="Regular Data Maintenance" fre="Regular Data Maintenance" contentUpdated="1/5/2013 9:19:14 AM" contentUpdatedPerson="PHILIP.STANG"><access contentAccessed="1/3/2013 9:25:01 AM" contentAccessedPerson="PHILIP.STANG"/><access contentAccessed="1/5/2013 9:13:09 AM" contentAccessedPerson="PHILIP.STANG"/><access contentAccessed="1/5/2013 9:15:29 AM" contentAccessedPerson="PHILIP.STANG"/><access contentAccessed="1/5/2013 9:18:37 AM" contentAccessedPerson="PHILIP.STANG"/><access contentAccessed="1/24/2013 4:49:19 PM" contentAccessedPerson=""/></page><page id="8250" type="leaf" path="8250.asp" eng="New Activity Wizard (NAW) Screens" fre="New Activity Wizard (NAW) Screens" contentUpdated="2/8/2013 4:32:49 PM" contentUpdatedPerson="PHILIP.STANG" pgCSS=""><access contentAccessed="2/8/2013 4:32:38 PM" contentAccessedPerson="PHILIP.STANG"/></page><page id="8251" type="leaf" path="8251.asp" eng="... save a document as a draft" fre="... save a document as a draft"/><page id="8252" type="leaf" path="8252.asp" eng="... see Activities/Documents of cross-referenced files" fre="... see Activities/Documents of cross-referenced files" contentUpdated="12/10/2012 8:34:05 AM" contentUpdatedPerson="PHILIP.STANG"><access contentAccessed="12/10/2012 8:09:45 AM" contentAccessedPerson="PHILIP.STANG"/></page><page id="8253" type="node" path="8253.asp" eng="Legal Advisory" fre="Legal Advisory"/><page id="8254" type="node" path="8254.asp" eng="Medical Advisory" fre="Medical Advisory"/><page id="8255" type="node" path="8255.asp" eng="Policies" fre="Policies"/><page id="8256" type="leaf" path="8256.asp" eng="Summary Dismissal" fre="Summary Dismissal" contentUpdated="12/28/2012 2:48:38 PM" contentUpdatedPerson="PHILIP.STANG"><access contentAccessed="12/28/2012 2:47:49 PM" contentAccessedPerson="PHILIP.STANG"/><access contentAccessed="1/9/2013 2:49:04 PM" contentAccessedPerson="CORY"/></page><page id="8257" type="node" path="8257.asp" eng="Procedures" fre="Procedures"/><page id="8282" type="leaf" path="8282.asp" eng="... mark a document as final/read-only" fre="... mark a document as final/read-only"/><page id="8283" type="node" path="8283.asp" eng="Administering this Deskbook" fre="Administering this Deskbook"/><page id="8284" type="leaf" path="8284.asp" eng="How to Export Multiple Pages to a Printable Version" fre="How to Export Multiple Pages to a Printable Version" contentUpdated="1/24/2013 5:03:37 PM" contentUpdatedPerson="" pgCSS=""><access contentAccessed="1/24/2013 4:52:55 PM" contentAccessedPerson=""/><access contentAccessed="1/24/2013 5:03:26 PM" contentAccessedPerson=""/><access contentAccessed="8/23/2013 3:44:56 PM" contentAccessedPerson=""/><access contentAccessed="8/23/2013 3:47:05 PM" contentAccessedPerson=""/><access contentAccessed="8/23/2013 3:48:51 PM" contentAccessedPerson=""/><access contentAccessed="8/23/2013 3:50:02 PM" contentAccessedPerson=""/></page><page id="8285" type="node" path="8285.asp" eng="Look-up Tables" fre="Look-up Tables"/><page id="8286" type="leaf" path="8286.asp" eng="File Meta-type Table" fre="File Meta-type Table" contentUpdated="1/24/2013 5:34:53 PM" contentUpdatedPerson="" pgCSS=""><access contentAccessed="1/24/2013 5:26:29 PM" contentAccessedPerson=""/></page><page id="8287" type="leaf" path="8287.asp" eng="Overview" fre="Overview" contentUpdated="1/29/2013 4:27:45 PM" contentUpdatedPerson="" pgCSS=""><access contentAccessed="1/24/2013 10:11:11 PM" contentAccessedPerson=""/><access contentAccessed="1/29/2013 2:16:21 PM" contentAccessedPerson=""/><access contentAccessed="1/29/2013 4:25:15 PM" contentAccessedPerson=""/></page><page id="8288" type="leaf" path="8288.asp" eng="... navigate between activities and documents" fre="... navigate between activities and documents" contentUpdated="1/24/2013 10:20:33 PM" contentUpdatedPerson="" pgCSS=""><access contentAccessed="1/24/2013 10:19:03 PM" contentAccessedPerson=""/></page><page id="8289" type="leaf" path="8289.asp" eng="Atrium Explorer Pop-up Window" fre="Atrium Explorer Pop-up Window" contentUpdated="2/5/2013 9:48:08 AM" contentUpdatedPerson="JEAN" pgCSS=""><access contentAccessed="1/29/2013 3:03:51 PM" contentAccessedPerson=""/><access contentAccessed="2/5/2013 9:48:00 AM" contentAccessedPerson="JEAN"/></page><page id="8290" type="leaf" path="8290.asp" eng="... add an Important Message to a file" fre="... add an Important Message to a file"/><page id="8292" type="leaf" path="8292.asp" eng="... remove an Important Message from a file" fre="... remove an Important Message from a file"/><page id="8299" type="leaf" path="8299.asp" eng="18(1)(a) - Availability and Suitable Employment" fre="18(1)(a) - Disponibilité et Emploi Convenable" contentUpdated="6/11/2013 3:20:34 PM" contentUpdatedPerson="" pgCSS=""><access contentAccessed="5/31/2013 9:09:31 AM" contentAccessedPerson="CORY"/><access contentAccessed="5/31/2013 9:10:06 AM" contentAccessedPerson="CORY"/><access contentAccessed="5/31/2013 11:34:53 AM" contentAccessedPerson=""/><access contentAccessed="6/1/2013 8:52:03 AM" contentAccessedPerson="CORY"/><access contentAccessed="6/1/2013 9:49:52 AM" contentAccessedPerson="CORY"/><access contentAccessed="6/3/2013 8:45:35 AM" contentAccessedPerson="CORY"/><access contentAccessed="6/4/2013 9:55:42 AM" contentAccessedPerson="CORY"/><access contentAccessed="6/4/2013 10:27:17 AM" contentAccessedPerson="CORY"/><access contentAccessed="6/4/2013 1:04:35 PM" contentAccessedPerson="CORY"/><access contentAccessed="6/4/2013 1:05:34 PM" contentAccessedPerson="CORY"/><access contentAccessed="6/5/2013 8:20:42 AM" contentAccessedPerson="CORY"/><access contentAccessed="6/5/2013 8:20:47 AM" contentAccessedPerson="CORY"/><access contentAccessed="6/5/2013 11:47:02 AM" contentAccessedPerson="CORY"/><access contentAccessed="6/5/2013 11:47:48 AM" contentAccessedPerson="CORY"/><access contentAccessed="6/5/2013 12:53:02 PM" contentAccessedPerson="CORY"/><access contentAccessed="6/5/2013 12:53:06 PM" contentAccessedPerson="CORY"/><access contentAccessed="6/11/2013 1:57:57 PM" contentAccessedPerson="CORY"/><access contentAccessed="6/11/2013 1:58:03 PM" contentAccessedPerson="CORY"/></page></pages>
